<?xml version="1.0" encoding="UTF-8"?>
<MF0 version="1.1" packageUris="http://schema.mathworks.com/mf0/ci/19700101 http://schema.mathworks.com/mf0/sl_modelref_info/R2025b http://schema.mathworks.com/mf0/slexec_mm_sto/R2025a_202404151030 http://schema.mathworks.com/mf0/sltp_mm/R2025b_202504071000">
  <ModelRefInfoRepo.ModelRefInfoRoot type="ModelRefInfoRepo.ModelRefInfoRoot" uuid="23b19977-1073-46b0-972d-f2efa65dae4b">
    <JITEngines>s01apsCIoAErJ91hnDINFLD</JITEngines>
    <JITEngines>sAB24QXOpcfQQF1rnO1MdAE</JITEngines>
    <JITEngines>sGNwhRyIISaf5QO6CXzg3BD</JITEngines>
    <JITEngines>sJPuk4MAONqOLVlm2AC6aY</JITEngines>
    <JITEngines>sVDbNTQZWSL30uU8naMYlBC</JITEngines>
    <JITEngines>sXegvx29j0rFYgZFLkqhvoF</JITEngines>
    <JITEngines>sXpZX1ohzw3puAKafCnWbME</JITEngines>
    <JITEngines>schrm49aVCflVUFWuwJrTcG</JITEngines>
    <JITEngines>se09mz6hN4V2D2VdfUorhe</JITEngines>
    <JITEngines>sjZADr1l7SFTuKZs2wD6XYF</JITEngines>
    <JITEngines>sxD7Hu62xeXlBVQKTTsQFqG</JITEngines>
    <calibrationData type="ModelRefInfoRepo.CalibrationData" uuid="219c68bf-2c9b-47ea-9098-c8b5f37cf27d">
      <InternalData>[{&quot;Name&quot;:&quot;e2e_checksum_disabled&quot;,&quot;Profile&quot;:&quot;&quot;},{&quot;Name&quot;:&quot;e2e_checksum_disabled&quot;,&quot;Profile&quot;:&quot;&quot;},{&quot;Name&quot;:&quot;pos_offset_a&quot;,&quot;Profile&quot;:&quot;&quot;},{&quot;Name&quot;:&quot;pos_offset_b&quot;,&quot;Profile&quot;:&quot;&quot;},{&quot;Name&quot;:&quot;e2e_checksum_disabled&quot;,&quot;Profile&quot;:&quot;&quot;},{&quot;Name&quot;:&quot;&quot;,&quot;Profile&quot;:&quot;&quot;},{&quot;Name&quot;:&quot;&quot;,&quot;Profile&quot;:&quot;&quot;},{&quot;Name&quot;:&quot;&quot;,&quot;Profile&quot;:&quot;&quot;},{&quot;Name&quot;:&quot;&quot;,&quot;Profile&quot;:&quot;&quot;},{&quot;Name&quot;:&quot;&quot;,&quot;Profile&quot;:&quot;&quot;},{&quot;Name&quot;:&quot;&quot;,&quot;Profile&quot;:&quot;&quot;},{&quot;Name&quot;:&quot;&quot;,&quot;Profile&quot;:&quot;&quot;},{&quot;Name&quot;:&quot;&quot;,&quot;Profile&quot;:&quot;&quot;},{&quot;Name&quot;:&quot;&quot;,&quot;Profile&quot;:&quot;&quot;},{&quot;Name&quot;:&quot;&quot;,&quot;Profile&quot;:&quot;&quot;},{&quot;Name&quot;:&quot;&quot;,&quot;Profile&quot;:&quot;&quot;},{&quot;Name&quot;:&quot;&quot;,&quot;Profile&quot;:&quot;&quot;},{&quot;Name&quot;:&quot;&quot;,&quot;Profile&quot;:&quot;&quot;},{&quot;Name&quot;:&quot;&quot;,&quot;Profile&quot;:&quot;&quot;}]</InternalData>
      <ModelName>GVCU_HIL_simscape</ModelName>
    </calibrationData>
    <childModelRefInfo type="ModelRefInfoRepo.ChildModelRefInfo" uuid="11510bee-86a3-4fc6-90e5-7ae8b301c10c">
      <modelName>GVCU_HIL_simscape</modelName>
      <modelPath>GVCU_HIL_simscape</modelPath>
    </childModelRefInfo>
    <clockResolutions type="ModelRefInfoRepo.ClockResolutionInfo" uuid="0f467852-e716-4ecd-86ef-48434a4db05c">
      <rateIdx>1</rateIdx>
      <resolution>.0002</resolution>
      <source>DeducedFromSampleTime</source>
    </clockResolutions>
    <compDerivCacheNeedsReset>false</compDerivCacheNeedsReset>
    <compZcCacheNeedsReset>false</compZcCacheNeedsReset>
    <compiledTFinal>2474.0</compiledTFinal>
    <dataSourceInfo type="ModelRefInfoRepo.DataSourceInfo" uuid="0dd9fd9b-8c41-4b19-814d-36c8c358d95d">
      <dataSources type="ModelRefInfoRepo.SourceInfo" uuid="4c358d68-cc85-49f9-95df-4b7349984670">
        <includeAllSections>true</includeAllSections>
        <sourceName>base workspace</sourceName>
        <type>BaseWorkspace</type>
      </dataSources>
      <modelName>GVCU_HIL_simscape</modelName>
    </dataSourceInfo>
    <dataTransferInfos>AAFJTQAAAAAOAAAAOAAAAAYAAAAIAAAAAgAAAAAAAAAFAAAACAAAAAAAAAABAAAAAQAAAAAAAAAFAAQAAQAAAAEAAAAAAAAA</dataTransferInfos>
    <defaultsCMapping>{&quot;Inports&quot;:&quot;{\&quot;Name\&quot;:\&quot;Default\&quot;,\&quot;Checksum\&quot;:\&quot;Default\&quot;,\&quot;PerInstancePropertiesChecksum\&quot;:\&quot;\&quot;,\&quot;MemorySectionName\&quot;:\&quot;None\&quot;,\&quot;MemorySectionChecksum\&quot;:\&quot;None\&quot;}&quot;,&quot;Outports&quot;:&quot;{\&quot;Name\&quot;:\&quot;Default\&quot;,\&quot;Checksum\&quot;:\&quot;Default\&quot;,\&quot;PerInstancePropertiesChecksum\&quot;:\&quot;\&quot;,\&quot;MemorySectionName\&quot;:\&quot;None\&quot;,\&quot;MemorySectionChecksum\&quot;:\&quot;None\&quot;}&quot;,&quot;ParameterArguments&quot;:&quot;{\&quot;Name\&quot;:\&quot;Default\&quot;,\&quot;Checksum\&quot;:\&quot;Default\&quot;,\&quot;PerInstancePropertiesChecksum\&quot;:\&quot;\&quot;,\&quot;MemorySectionName\&quot;:\&quot;None\&quot;,\&quot;MemorySectionChecksum\&quot;:\&quot;None\&quot;}&quot;,&quot;LocalParameters&quot;:&quot;{\&quot;Name\&quot;:\&quot;Default\&quot;,\&quot;Checksum\&quot;:\&quot;Default\&quot;,\&quot;PerInstancePropertiesChecksum\&quot;:\&quot;\&quot;,\&quot;MemorySectionName\&quot;:\&quot;None\&quot;,\&quot;MemorySectionChecksum\&quot;:\&quot;None\&quot;}&quot;,&quot;GlobalParameters&quot;:&quot;{\&quot;Name\&quot;:\&quot;Default\&quot;,\&quot;Checksum\&quot;:\&quot;Default\&quot;,\&quot;PerInstancePropertiesChecksum\&quot;:\&quot;\&quot;,\&quot;MemorySectionName\&quot;:\&quot;None\&quot;,\&quot;MemorySectionChecksum\&quot;:\&quot;None\&quot;}&quot;,&quot;InternalData&quot;:&quot;{\&quot;Name\&quot;:\&quot;Default\&quot;,\&quot;Checksum\&quot;:\&quot;Default\&quot;,\&quot;PerInstancePropertiesChecksum\&quot;:\&quot;\&quot;,\&quot;MemorySectionName\&quot;:\&quot;None\&quot;,\&quot;MemorySectionChecksum\&quot;:\&quot;None\&quot;}&quot;,&quot;SharedLocalDataStores&quot;:&quot;{\&quot;Name\&quot;:\&quot;Default\&quot;,\&quot;Checksum\&quot;:\&quot;Default\&quot;,\&quot;PerInstancePropertiesChecksum\&quot;:\&quot;\&quot;,\&quot;MemorySectionName\&quot;:\&quot;None\&quot;,\&quot;MemorySectionChecksum\&quot;:\&quot;None\&quot;}&quot;,&quot;GlobalDataStores&quot;:&quot;{\&quot;Name\&quot;:\&quot;Default\&quot;,\&quot;Checksum\&quot;:\&quot;Default\&quot;,\&quot;PerInstancePropertiesChecksum\&quot;:\&quot;\&quot;,\&quot;MemorySectionName\&quot;:\&quot;None\&quot;,\&quot;MemorySectionChecksum\&quot;:\&quot;None\&quot;}&quot;,&quot;Constants&quot;:&quot;{\&quot;Name\&quot;:\&quot;Default\&quot;,\&quot;Checksum\&quot;:\&quot;Default\&quot;,\&quot;PerInstancePropertiesChecksum\&quot;:\&quot;\&quot;,\&quot;MemorySectionName\&quot;:\&quot;None\&quot;,\&quot;MemorySectionChecksum\&quot;:\&quot;None\&quot;}&quot;,&quot;DataTransfers&quot;:&quot;{\&quot;Name\&quot;:\&quot;Default\&quot;,\&quot;Checksum\&quot;:\&quot;Default\&quot;,\&quot;PerInstancePropertiesChecksum\&quot;:\&quot;\&quot;,\&quot;MemorySectionName\&quot;:\&quot;None\&quot;,\&quot;MemorySectionChecksum\&quot;:\&quot;None\&quot;}&quot;,&quot;ModelData&quot;:&quot;{\&quot;Name\&quot;:\&quot;Default\&quot;,\&quot;Checksum\&quot;:\&quot;Default\&quot;,\&quot;PerInstancePropertiesChecksum\&quot;:\&quot;\&quot;,\&quot;MemorySectionName\&quot;:\&quot;None\&quot;,\&quot;MemorySectionChecksum\&quot;:\&quot;None\&quot;}&quot;,&quot;InitializeTerminate&quot;:&quot;{\&quot;Name\&quot;:\&quot;Default\&quot;,\&quot;Checksum\&quot;:\&quot;Default\&quot;,\&quot;PerInstancePropertiesChecksum\&quot;:\&quot;\&quot;,\&quot;MemorySectionName\&quot;:\&quot;None\&quot;,\&quot;MemorySectionChecksum\&quot;:\&quot;None\&quot;}&quot;,&quot;Execution&quot;:&quot;{\&quot;Name\&quot;:\&quot;Default\&quot;,\&quot;Checksum\&quot;:\&quot;Default\&quot;,\&quot;PerInstancePropertiesChecksum\&quot;:\&quot;\&quot;,\&quot;MemorySectionName\&quot;:\&quot;None\&quot;,\&quot;MemorySectionChecksum\&quot;:\&quot;None\&quot;}&quot;,&quot;SharedUtility&quot;:&quot;{\&quot;Name\&quot;:\&quot;Default\&quot;,\&quot;Checksum\&quot;:\&quot;Default\&quot;,\&quot;PerInstancePropertiesChecksum\&quot;:\&quot;\&quot;,\&quot;MemorySectionName\&quot;:\&quot;None\&quot;,\&quot;MemorySectionChecksum\&quot;:\&quot;None\&quot;}&quot;}</defaultsCMapping>
    <fastestNoncontSigFeedingDerivPorts>.0002</fastestNoncontSigFeedingDerivPorts>
    <globalVariables>MEM</globalVariables>
    <globalVariables>acc_pedal_data</globalVariables>
    <globalVariables>acc_pedal_time</globalVariables>
    <globalVariables>aero</globalVariables>
    <globalVariables>bat</globalVariables>
    <globalVariables>brake</globalVariables>
    <globalVariables>brk_pedal_data</globalVariables>
    <globalVariables>brk_pedal_time</globalVariables>
    <globalVariables>config</globalVariables>
    <globalVariables>cycle_len</globalVariables>
    <globalVariables>cycle_speed_matrix</globalVariables>
    <globalVariables>cycle_time_matrix</globalVariables>
    <globalVariables>eff_EM_loss</globalVariables>
    <globalVariables>eff_EM_speed</globalVariables>
    <globalVariables>eff_EM_torque</globalVariables>
    <globalVariables>front</globalVariables>
    <globalVariables>plane</globalVariables>
    <globalVariables>powertrain</globalVariables>
    <globalVariables>rear</globalVariables>
    <globalVariables>vEM</globalVariables>
    <globalVariables>veh</globalVariables>
    <globalVariables>veh_speed_data</globalVariables>
    <globalVariables>veh_speed_time</globalVariables>
    <globalVariables>vis</globalVariables>
    <hasBlockWithPeriodicDiscreteSampleTime>true</hasBlockWithPeriodicDiscreteSampleTime>
    <hasBwsAccessed>true</hasBwsAccessed>
    <hasContinuousSampleTime>true</hasContinuousSampleTime>
    <hasInlineVariantBlock>true</hasInlineVariantBlock>
    <hasNonVirtualConstantTs>true</hasNonVirtualConstantTs>
    <hasNoncontSigFeedingDerivPorts>true</hasNoncontSigFeedingDerivPorts>
    <hasStatesModifiedInOutputUpdate>true</hasStatesModifiedInOutputUpdate>
    <hasVariantModelOrSubsystem>true</hasVariantModelOrSubsystem>
    <isBdInSimModeForSimCodegenVariants>false</isBdInSimModeForSimCodegenVariants>
    <loggingSaveFormat>2</loggingSaveFormat>
    <massMatrixNzMax>109</massMatrixNzMax>
    <maxFreqHz>-1.0</maxFreqHz>
    <needAbsoluteTimeDisallowInitPort>true</needAbsoluteTimeDisallowInitPort>
    <needsAbsoluteTime>true</needsAbsoluteTime>
    <nonTunableVariables>aero</nonTunableVariables>
    <nonTunableVariables>config</nonTunableVariables>
    <nonTunableVariables>eff_EM_loss</nonTunableVariables>
    <nonTunableVariables>plane</nonTunableVariables>
    <nonTunableVariables>powertrain</nonTunableVariables>
    <nonTunableVariables>veh</nonTunableVariables>
    <nonTunableVariables>vis</nonTunableVariables>
    <numCStateRecs>104</numCStateRecs>
    <numContinuousStates>109</numContinuousStates>
    <numDStateRecs>277</numDStateRecs>
    <numDStateRecsInMdl>277</numDStateRecsInMdl>
    <numDataInputPorts>0</numDataInputPorts>
    <numLoggableCStateRecs>104</numLoggableCStateRecs>
    <numLoggableDStateRecs>277</numLoggableDStateRecs>
    <numLoggableDStateRecsInMdl>277</numLoggableDStateRecsInMdl>
    <numLoggableJacobianDStates>745</numLoggableJacobianDStates>
    <runtimeNonFcnCallRateInfos type="ModelRefInfoRepo.RateInfo">
      <compiled>true</compiled>
      <needAbsoluteTime>true</needAbsoluteTime>
      <period>0.0</period>
      <priority>40</priority>
      <rateIdx>0</rateIdx>
    </runtimeNonFcnCallRateInfos>
    <runtimeNonFcnCallRateInfos type="ModelRefInfoRepo.RateInfo">
      <compiled>true</compiled>
      <needAbsoluteTime>true</needAbsoluteTime>
      <nonFcnCallPartitionName>Cont</nonFcnCallPartitionName>
      <period>.0002</period>
      <priority>40</priority>
      <rateIdx>1</rateIdx>
    </runtimeNonFcnCallRateInfos>
    <runtimeNonFcnCallRateInfos type="ModelRefInfoRepo.RateInfo">
      <compiled>true</compiled>
      <nonFcnCallPartitionName>Cont</nonFcnCallPartitionName>
      <period>.0004</period>
      <priority>40</priority>
      <rateIdx>2</rateIdx>
    </runtimeNonFcnCallRateInfos>
    <runtimeNonFcnCallRateInfos type="ModelRefInfoRepo.RateInfo">
      <compiled>true</compiled>
      <nonFcnCallPartitionName>Cont</nonFcnCallPartitionName>
      <period>.001</period>
      <priority>40</priority>
      <rateIdx>3</rateIdx>
    </runtimeNonFcnCallRateInfos>
    <runtimeNonFcnCallRateInfos type="ModelRefInfoRepo.RateInfo">
      <compiled>true</compiled>
      <nonFcnCallPartitionName>Cont</nonFcnCallPartitionName>
      <period>.002</period>
      <priority>40</priority>
      <rateIdx>4</rateIdx>
    </runtimeNonFcnCallRateInfos>
    <runtimeNonFcnCallRateInfos type="ModelRefInfoRepo.RateInfo">
      <compiled>true</compiled>
      <nonFcnCallPartitionName>Cont</nonFcnCallPartitionName>
      <period>.004</period>
      <priority>40</priority>
      <rateIdx>5</rateIdx>
    </runtimeNonFcnCallRateInfos>
    <runtimeNonFcnCallRateInfos type="ModelRefInfoRepo.RateInfo">
      <compiled>true</compiled>
      <nonFcnCallPartitionName>Cont</nonFcnCallPartitionName>
      <period>.005</period>
      <priority>40</priority>
      <rateIdx>6</rateIdx>
    </runtimeNonFcnCallRateInfos>
    <runtimeNonFcnCallRateInfos type="ModelRefInfoRepo.RateInfo">
      <compiled>true</compiled>
      <nonFcnCallPartitionName>Cont</nonFcnCallPartitionName>
      <period>.01</period>
      <priority>40</priority>
      <rateIdx>7</rateIdx>
    </runtimeNonFcnCallRateInfos>
    <runtimeNonFcnCallRateInfos type="ModelRefInfoRepo.RateInfo">
      <compiled>true</compiled>
      <nonFcnCallPartitionName>Cont</nonFcnCallPartitionName>
      <period>.1</period>
      <priority>40</priority>
      <rateIdx>8</rateIdx>
    </runtimeNonFcnCallRateInfos>
    <runtimeNonFcnCallRateInfos type="ModelRefInfoRepo.RateInfo">
      <compiled>true</compiled>
      <nonFcnCallPartitionName>Cont</nonFcnCallPartitionName>
      <period>1.0</period>
      <priority>40</priority>
      <rateIdx>9</rateIdx>
    </runtimeNonFcnCallRateInfos>
    <sampleTimeInheritanceRule>2</sampleTimeInheritanceRule>
    <solverStatusFlags>323</solverStatusFlags>
    <solverUpdateJacobianAtReset>true</solverUpdateJacobianAtReset>
    <timingAndTaskingRegistry>&lt;?xml version=&quot;1.0&quot;?&gt;
&lt;slexec_sto version=&quot;1.1&quot; packageUris=&quot;http://schema.mathworks.com/mf0/slexec_mm_sto/R2025a_202404151030&quot;&gt;
  &lt;sto.Registry type=&quot;sto.Registry&quot; uuid=&quot;179917f1-2c3e-4454-beba-180356239368&quot;&gt;
    &lt;executionSpec&gt;Undetermined&lt;/executionSpec&gt;
    &lt;identifier&gt;GVCU_HIL_simscape&lt;/identifier&gt;
    &lt;clockRegistry type=&quot;sto.ClockRegistry&quot; uuid=&quot;9d324dfd-8ae1-455e-9f11-b82e62850f69&quot;&gt;
      &lt;clocks type=&quot;sto.Timer&quot; uuid=&quot;8bfb811c-3316-4403-8c50-dd1490ad4395&quot;&gt;
        &lt;computedFundamentalDiscretePeriod&gt;.0002&lt;/computedFundamentalDiscretePeriod&gt;
        &lt;fastestDiscreteRate type=&quot;sto.ClassicPeriodicDiscreteRate&quot; uuid=&quot;ff2bb47e-a0e2-4948-b96d-f350e6ecab54&quot;/&gt;
        &lt;isDefaultTimer&gt;true&lt;/isDefaultTimer&gt;
        &lt;resolution&gt;.0002&lt;/resolution&gt;
        &lt;timeAdvanceMode&gt;FixedStep&lt;/timeAdvanceMode&gt;
        &lt;identifier&gt;GVCU_HIL_simscape::defaultTimer&lt;/identifier&gt;
        &lt;rates type=&quot;sto.ContinuousRate&quot; uuid=&quot;0c571f0d-962c-486e-bf1f-c293af51d531&quot;&gt;
          &lt;annotation&gt;Cont&lt;/annotation&gt;
          &lt;clockId&gt;GVCU_HIL_simscape::defaultTimer&lt;/clockId&gt;
          &lt;colorIndex&gt;-1&lt;/colorIndex&gt;
          &lt;description&gt;Continuous&lt;/description&gt;
          &lt;taskId&gt;_task0&lt;/taskId&gt;
          &lt;rateSpec type=&quot;sto.RateSpec&quot; uuid=&quot;f0b5970f-0a31-45fb-9f16-64f0eb1b2a49&quot;/&gt;
        &lt;/rates&gt;
        &lt;rates type=&quot;sto.ClassicPeriodicDiscreteRate&quot; uuid=&quot;ff2bb47e-a0e2-4948-b96d-f350e6ecab54&quot;&gt;
          &lt;annotation&gt;D1&lt;/annotation&gt;
          &lt;clockId&gt;GVCU_HIL_simscape::defaultTimer&lt;/clockId&gt;
          &lt;description&gt;Discrete 1&lt;/description&gt;
          &lt;rateIdx&gt;1&lt;/rateIdx&gt;
          &lt;taskId&gt;_task0&lt;/taskId&gt;
          &lt;rateSpec type=&quot;sto.RateSpec&quot; uuid=&quot;b6ce88ba-95e5-470b-a3e2-ee304feb0002&quot;&gt;
            &lt;period&gt;.0002&lt;/period&gt;
            &lt;rateType&gt;ClassicPeriodicDiscrete&lt;/rateType&gt;
          &lt;/rateSpec&gt;
        &lt;/rates&gt;
        &lt;rates type=&quot;sto.ClassicPeriodicDiscreteRate&quot; uuid=&quot;1cf0bc50-c528-4eb0-be69-594f05281321&quot;&gt;
          &lt;annotation&gt;D2&lt;/annotation&gt;
          &lt;clockId&gt;GVCU_HIL_simscape::defaultTimer&lt;/clockId&gt;
          &lt;colorIndex&gt;1&lt;/colorIndex&gt;
          &lt;description&gt;Discrete 2&lt;/description&gt;
          &lt;rateIdx&gt;2&lt;/rateIdx&gt;
          &lt;taskId&gt;_task0&lt;/taskId&gt;
          &lt;rateSpec type=&quot;sto.RateSpec&quot; uuid=&quot;6bb2b081-bd65-4407-9149-a546aa1326e9&quot;&gt;
            &lt;period&gt;.0004&lt;/period&gt;
            &lt;rateType&gt;ClassicPeriodicDiscrete&lt;/rateType&gt;
          &lt;/rateSpec&gt;
        &lt;/rates&gt;
        &lt;rates type=&quot;sto.ClassicPeriodicDiscreteRate&quot; uuid=&quot;ac02e74b-99cd-4a89-8774-378bb96eeced&quot;&gt;
          &lt;annotation&gt;D3&lt;/annotation&gt;
          &lt;clockId&gt;GVCU_HIL_simscape::defaultTimer&lt;/clockId&gt;
          &lt;colorIndex&gt;2&lt;/colorIndex&gt;
          &lt;description&gt;Discrete 3&lt;/description&gt;
          &lt;rateIdx&gt;3&lt;/rateIdx&gt;
          &lt;taskId&gt;_task0&lt;/taskId&gt;
          &lt;rateSpec type=&quot;sto.RateSpec&quot; uuid=&quot;6a82cccc-4138-42f2-bd7c-1a6decff6553&quot;&gt;
            &lt;period&gt;.001&lt;/period&gt;
            &lt;rateType&gt;ClassicPeriodicDiscrete&lt;/rateType&gt;
          &lt;/rateSpec&gt;
        &lt;/rates&gt;
        &lt;rates type=&quot;sto.ClassicPeriodicDiscreteRate&quot; uuid=&quot;81078203-3397-4f6a-a331-8ae36667ebd0&quot;&gt;
          &lt;annotation&gt;D4&lt;/annotation&gt;
          &lt;clockId&gt;GVCU_HIL_simscape::defaultTimer&lt;/clockId&gt;
          &lt;colorIndex&gt;3&lt;/colorIndex&gt;
          &lt;description&gt;Discrete 4&lt;/description&gt;
          &lt;rateIdx&gt;4&lt;/rateIdx&gt;
          &lt;taskId&gt;_task0&lt;/taskId&gt;
          &lt;rateSpec type=&quot;sto.RateSpec&quot; uuid=&quot;b567216b-0827-4c5e-a9df-b320faf5db02&quot;&gt;
            &lt;period&gt;.002&lt;/period&gt;
            &lt;rateType&gt;ClassicPeriodicDiscrete&lt;/rateType&gt;
          &lt;/rateSpec&gt;
        &lt;/rates&gt;
        &lt;rates type=&quot;sto.ClassicPeriodicDiscreteRate&quot; uuid=&quot;aeb9e078-bf52-481f-a92b-d5e71bfd0128&quot;&gt;
          &lt;annotation&gt;D5&lt;/annotation&gt;
          &lt;clockId&gt;GVCU_HIL_simscape::defaultTimer&lt;/clockId&gt;
          &lt;colorIndex&gt;4&lt;/colorIndex&gt;
          &lt;description&gt;Discrete 5&lt;/description&gt;
          &lt;rateIdx&gt;5&lt;/rateIdx&gt;
          &lt;taskId&gt;_task0&lt;/taskId&gt;
          &lt;rateSpec type=&quot;sto.RateSpec&quot; uuid=&quot;60c61bed-8d9b-457d-a98a-10574e421e72&quot;&gt;
            &lt;period&gt;.004&lt;/period&gt;
            &lt;rateType&gt;ClassicPeriodicDiscrete&lt;/rateType&gt;
          &lt;/rateSpec&gt;
        &lt;/rates&gt;
        &lt;rates type=&quot;sto.ClassicPeriodicDiscreteRate&quot; uuid=&quot;cf97b87d-fd9d-4e18-9a7e-cfecbf4a0509&quot;&gt;
          &lt;annotation&gt;D6&lt;/annotation&gt;
          &lt;clockId&gt;GVCU_HIL_simscape::defaultTimer&lt;/clockId&gt;
          &lt;colorIndex&gt;5&lt;/colorIndex&gt;
          &lt;description&gt;Discrete 6&lt;/description&gt;
          &lt;rateIdx&gt;6&lt;/rateIdx&gt;
          &lt;taskId&gt;_task0&lt;/taskId&gt;
          &lt;rateSpec type=&quot;sto.RateSpec&quot; uuid=&quot;fdaa6195-bb7b-41c7-b687-1a9c236a8abd&quot;&gt;
            &lt;period&gt;.005&lt;/period&gt;
            &lt;rateType&gt;ClassicPeriodicDiscrete&lt;/rateType&gt;
          &lt;/rateSpec&gt;
        &lt;/rates&gt;
        &lt;rates type=&quot;sto.ClassicPeriodicDiscreteRate&quot; uuid=&quot;5e1c0547-cf85-4e73-9a6d-1bd88c5a416c&quot;&gt;
          &lt;annotation&gt;D7&lt;/annotation&gt;
          &lt;clockId&gt;GVCU_HIL_simscape::defaultTimer&lt;/clockId&gt;
          &lt;colorIndex&gt;6&lt;/colorIndex&gt;
          &lt;description&gt;Discrete 7&lt;/description&gt;
          &lt;rateIdx&gt;7&lt;/rateIdx&gt;
          &lt;taskId&gt;_task0&lt;/taskId&gt;
          &lt;rateSpec type=&quot;sto.RateSpec&quot; uuid=&quot;800d84c3-679f-4efe-ba5b-86331c6ff3a3&quot;&gt;
            &lt;period&gt;.01&lt;/period&gt;
            &lt;rateType&gt;ClassicPeriodicDiscrete&lt;/rateType&gt;
          &lt;/rateSpec&gt;
        &lt;/rates&gt;
        &lt;rates type=&quot;sto.ClassicPeriodicDiscreteRate&quot; uuid=&quot;8010da0d-9075-4e64-98b3-e3e546d05bcd&quot;&gt;
          &lt;annotation&gt;D8&lt;/annotation&gt;
          &lt;clockId&gt;GVCU_HIL_simscape::defaultTimer&lt;/clockId&gt;
          &lt;colorIndex&gt;7&lt;/colorIndex&gt;
          &lt;description&gt;Discrete 8&lt;/description&gt;
          &lt;rateIdx&gt;8&lt;/rateIdx&gt;
          &lt;taskId&gt;_task0&lt;/taskId&gt;
          &lt;rateSpec type=&quot;sto.RateSpec&quot; uuid=&quot;48ec0f74-93b1-4a31-b5b3-1f496a504936&quot;&gt;
            &lt;period&gt;.1&lt;/period&gt;
            &lt;rateType&gt;ClassicPeriodicDiscrete&lt;/rateType&gt;
          &lt;/rateSpec&gt;
        &lt;/rates&gt;
        &lt;rates type=&quot;sto.ClassicPeriodicDiscreteRate&quot; uuid=&quot;39864c1c-6629-493a-9a89-b1d39abbae45&quot;&gt;
          &lt;annotation&gt;D9&lt;/annotation&gt;
          &lt;clockId&gt;GVCU_HIL_simscape::defaultTimer&lt;/clockId&gt;
          &lt;colorIndex&gt;8&lt;/colorIndex&gt;
          &lt;description&gt;Discrete 9&lt;/description&gt;
          &lt;rateIdx&gt;9&lt;/rateIdx&gt;
          &lt;taskId&gt;_task0&lt;/taskId&gt;
          &lt;rateSpec type=&quot;sto.RateSpec&quot; uuid=&quot;10902cd2-e956-4f39-aa16-0215fa20a935&quot;&gt;
            &lt;period&gt;1.0&lt;/period&gt;
            &lt;rateType&gt;ClassicPeriodicDiscrete&lt;/rateType&gt;
          &lt;/rateSpec&gt;
        &lt;/rates&gt;
        &lt;baseRate type=&quot;sto.ContinuousRate&quot; uuid=&quot;6510b80f-9e03-4fa2-8147-07ffd46b6ce5&quot;&gt;
          &lt;annotation&gt;Cont&lt;/annotation&gt;
          &lt;clockId&gt;GVCU_HIL_simscape::defaultTimer&lt;/clockId&gt;
          &lt;colorIndex&gt;-1&lt;/colorIndex&gt;
          &lt;description&gt;Continuous&lt;/description&gt;
          &lt;taskId&gt;_task0&lt;/taskId&gt;
          &lt;rateSpec type=&quot;sto.RateSpec&quot; uuid=&quot;35eb9864-23b5-43a6-806e-e186052c7988&quot;/&gt;
        &lt;/baseRate&gt;
      &lt;/clocks&gt;
      &lt;clocks type=&quot;sto.Event&quot; uuid=&quot;d57f363e-4d4f-42a4-bd75-a9704b921049&quot;&gt;
        &lt;eventType&gt;PARAMETER_CHANGE_EVENT&lt;/eventType&gt;
        &lt;cNum&gt;1&lt;/cNum&gt;
        &lt;clockType&gt;Event&lt;/clockType&gt;
        &lt;identifier&gt;ParameterChangeEvent&lt;/identifier&gt;
        &lt;rates type=&quot;sto.ModelWideEventRate&quot; uuid=&quot;e27308ad-770d-459d-9f48-8f323f3c7036&quot;&gt;
          &lt;annotation&gt;Inf&lt;/annotation&gt;
          &lt;clockId&gt;ParameterChangeEvent&lt;/clockId&gt;
          &lt;colorIndex&gt;-1&lt;/colorIndex&gt;
          &lt;description&gt;Constant&lt;/description&gt;
          &lt;rateIdx&gt;-1&lt;/rateIdx&gt;
          &lt;taskId&gt;ModelWideParameterChangeEvent&lt;/taskId&gt;
          &lt;useForExecution&gt;NotForExecution&lt;/useForExecution&gt;
          &lt;rateSpec type=&quot;sto.RateSpec&quot; uuid=&quot;5827015a-25ae-45e5-8430-bad2a4076002&quot;&gt;
            &lt;period&gt;inf&lt;/period&gt;
            &lt;rateType&gt;ModelWideParameterChangeEvent&lt;/rateType&gt;
          &lt;/rateSpec&gt;
        &lt;/rates&gt;
      &lt;/clocks&gt;
      &lt;timeAdvanceMode&gt;FixedStep&lt;/timeAdvanceMode&gt;
    &lt;/clockRegistry&gt;
    &lt;taskRegistry type=&quot;sto.TaskRegistry&quot; uuid=&quot;2a077ce8-0cd1-432b-a180-e59b3db91d47&quot;&gt;
      &lt;rootTaskHierarchyElements type=&quot;sto.Task&quot; uuid=&quot;eb6fb56f-3db8-4944-aafa-85e1e2c2e4e9&quot;&gt;
        &lt;isExplicit&gt;true&lt;/isExplicit&gt;
        &lt;rates type=&quot;sto.ModelWideEventRate&quot; uuid=&quot;b2a1fe26-a987-4000-a9f5-d46733afe5da&quot;&gt;
          &lt;annotation&gt;Inf&lt;/annotation&gt;
          &lt;clockId&gt;ParameterChangeEvent&lt;/clockId&gt;
          &lt;colorIndex&gt;-1&lt;/colorIndex&gt;
          &lt;description&gt;Constant&lt;/description&gt;
          &lt;rateIdx&gt;-1&lt;/rateIdx&gt;
          &lt;taskId&gt;ModelWideParameterChangeEvent&lt;/taskId&gt;
          &lt;useForExecution&gt;NotForExecution&lt;/useForExecution&gt;
          &lt;rateSpec type=&quot;sto.RateSpec&quot; uuid=&quot;a6b6a3bd-0ed1-45c7-b008-ebd289356a0a&quot;&gt;
            &lt;period&gt;inf&lt;/period&gt;
            &lt;rateType&gt;ModelWideParameterChangeEvent&lt;/rateType&gt;
          &lt;/rateSpec&gt;
        &lt;/rates&gt;
        &lt;schedulingClockId&gt;ParameterChangeEvent&lt;/schedulingClockId&gt;
        &lt;timeKeeperClockId&gt;GVCU_HIL_simscape::defaultTimer&lt;/timeKeeperClockId&gt;
        &lt;elementType&gt;Task&lt;/elementType&gt;
        &lt;identifier&gt;ModelWideParameterChangeEvent&lt;/identifier&gt;
        &lt;priority&gt;-1&lt;/priority&gt;
      &lt;/rootTaskHierarchyElements&gt;
      &lt;rootTaskHierarchyElements type=&quot;sto.Task&quot; uuid=&quot;aca23851-7538-454b-902a-a4eec945b78e&quot;&gt;
        &lt;isExecutable&gt;true&lt;/isExecutable&gt;
        &lt;orderIndex&gt;1&lt;/orderIndex&gt;
        &lt;rates type=&quot;sto.ContinuousRate&quot; uuid=&quot;9309606f-3d60-408d-bb64-3144a6fd50c2&quot;&gt;
          &lt;annotation&gt;Cont&lt;/annotation&gt;
          &lt;clockId&gt;GVCU_HIL_simscape::defaultTimer&lt;/clockId&gt;
          &lt;colorIndex&gt;-1&lt;/colorIndex&gt;
          &lt;description&gt;Continuous&lt;/description&gt;
          &lt;taskId&gt;_task0&lt;/taskId&gt;
          &lt;rateSpec type=&quot;sto.RateSpec&quot; uuid=&quot;c463ff55-84d7-4399-9b76-41fea0df33a2&quot;/&gt;
        &lt;/rates&gt;
        &lt;rates type=&quot;sto.ClassicPeriodicDiscreteRate&quot; uuid=&quot;445e3e90-d6c9-4c47-ab91-45ca88f1cc56&quot;&gt;
          &lt;annotation&gt;D1&lt;/annotation&gt;
          &lt;clockId&gt;GVCU_HIL_simscape::defaultTimer&lt;/clockId&gt;
          &lt;description&gt;Discrete 1&lt;/description&gt;
          &lt;rateIdx&gt;1&lt;/rateIdx&gt;
          &lt;taskId&gt;_task0&lt;/taskId&gt;
          &lt;rateSpec type=&quot;sto.RateSpec&quot; uuid=&quot;6e00a4ee-96ef-4cf5-9edb-393f2195ff29&quot;&gt;
            &lt;period&gt;.0002&lt;/period&gt;
            &lt;rateType&gt;ClassicPeriodicDiscrete&lt;/rateType&gt;
          &lt;/rateSpec&gt;
        &lt;/rates&gt;
        &lt;rates type=&quot;sto.ClassicPeriodicDiscreteRate&quot; uuid=&quot;a3644cf0-446d-46fb-b8ec-52cf09323eba&quot;&gt;
          &lt;annotation&gt;D2&lt;/annotation&gt;
          &lt;clockId&gt;GVCU_HIL_simscape::defaultTimer&lt;/clockId&gt;
          &lt;colorIndex&gt;1&lt;/colorIndex&gt;
          &lt;description&gt;Discrete 2&lt;/description&gt;
          &lt;rateIdx&gt;2&lt;/rateIdx&gt;
          &lt;taskId&gt;_task0&lt;/taskId&gt;
          &lt;rateSpec type=&quot;sto.RateSpec&quot; uuid=&quot;b3e0acb2-181b-4bf6-923c-bbae3a8435df&quot;&gt;
            &lt;period&gt;.0004&lt;/period&gt;
            &lt;rateType&gt;ClassicPeriodicDiscrete&lt;/rateType&gt;
          &lt;/rateSpec&gt;
        &lt;/rates&gt;
        &lt;rates type=&quot;sto.ClassicPeriodicDiscreteRate&quot; uuid=&quot;75834107-a348-4ab2-bee0-dceec8d56400&quot;&gt;
          &lt;annotation&gt;D3&lt;/annotation&gt;
          &lt;clockId&gt;GVCU_HIL_simscape::defaultTimer&lt;/clockId&gt;
          &lt;colorIndex&gt;2&lt;/colorIndex&gt;
          &lt;description&gt;Discrete 3&lt;/description&gt;
          &lt;rateIdx&gt;3&lt;/rateIdx&gt;
          &lt;taskId&gt;_task0&lt;/taskId&gt;
          &lt;rateSpec type=&quot;sto.RateSpec&quot; uuid=&quot;4ebffa68-3c36-4721-96af-e040f9361268&quot;&gt;
            &lt;period&gt;.001&lt;/period&gt;
            &lt;rateType&gt;ClassicPeriodicDiscrete&lt;/rateType&gt;
          &lt;/rateSpec&gt;
        &lt;/rates&gt;
        &lt;rates type=&quot;sto.ClassicPeriodicDiscreteRate&quot; uuid=&quot;38624dba-5212-4b77-a5a3-4ab8da8d11fd&quot;&gt;
          &lt;annotation&gt;D4&lt;/annotation&gt;
          &lt;clockId&gt;GVCU_HIL_simscape::defaultTimer&lt;/clockId&gt;
          &lt;colorIndex&gt;3&lt;/colorIndex&gt;
          &lt;description&gt;Discrete 4&lt;/description&gt;
          &lt;rateIdx&gt;4&lt;/rateIdx&gt;
          &lt;taskId&gt;_task0&lt;/taskId&gt;
          &lt;rateSpec type=&quot;sto.RateSpec&quot; uuid=&quot;610a9995-efd9-4349-807c-d7df094d385a&quot;&gt;
            &lt;period&gt;.002&lt;/period&gt;
            &lt;rateType&gt;ClassicPeriodicDiscrete&lt;/rateType&gt;
          &lt;/rateSpec&gt;
        &lt;/rates&gt;
        &lt;rates type=&quot;sto.ClassicPeriodicDiscreteRate&quot; uuid=&quot;3ee144c5-5612-4200-80bb-15a1dbdf09e0&quot;&gt;
          &lt;annotation&gt;D5&lt;/annotation&gt;
          &lt;clockId&gt;GVCU_HIL_simscape::defaultTimer&lt;/clockId&gt;
          &lt;colorIndex&gt;4&lt;/colorIndex&gt;
          &lt;description&gt;Discrete 5&lt;/description&gt;
          &lt;rateIdx&gt;5&lt;/rateIdx&gt;
          &lt;taskId&gt;_task0&lt;/taskId&gt;
          &lt;rateSpec type=&quot;sto.RateSpec&quot; uuid=&quot;b4d5726b-ae80-4ce8-bd5d-ffa827bbd82b&quot;&gt;
            &lt;period&gt;.004&lt;/period&gt;
            &lt;rateType&gt;ClassicPeriodicDiscrete&lt;/rateType&gt;
          &lt;/rateSpec&gt;
        &lt;/rates&gt;
        &lt;rates type=&quot;sto.ClassicPeriodicDiscreteRate&quot; uuid=&quot;1b35f165-db0d-4273-973c-29e1ea53f4bf&quot;&gt;
          &lt;annotation&gt;D6&lt;/annotation&gt;
          &lt;clockId&gt;GVCU_HIL_simscape::defaultTimer&lt;/clockId&gt;
          &lt;colorIndex&gt;5&lt;/colorIndex&gt;
          &lt;description&gt;Discrete 6&lt;/description&gt;
          &lt;rateIdx&gt;6&lt;/rateIdx&gt;
          &lt;taskId&gt;_task0&lt;/taskId&gt;
          &lt;rateSpec type=&quot;sto.RateSpec&quot; uuid=&quot;f42c155f-6119-4136-a33b-aadc2783b083&quot;&gt;
            &lt;period&gt;.005&lt;/period&gt;
            &lt;rateType&gt;ClassicPeriodicDiscrete&lt;/rateType&gt;
          &lt;/rateSpec&gt;
        &lt;/rates&gt;
        &lt;rates type=&quot;sto.ClassicPeriodicDiscreteRate&quot; uuid=&quot;e6cd1e8d-530b-4b34-8087-b00c5ad89cb5&quot;&gt;
          &lt;annotation&gt;D7&lt;/annotation&gt;
          &lt;clockId&gt;GVCU_HIL_simscape::defaultTimer&lt;/clockId&gt;
          &lt;colorIndex&gt;6&lt;/colorIndex&gt;
          &lt;description&gt;Discrete 7&lt;/description&gt;
          &lt;rateIdx&gt;7&lt;/rateIdx&gt;
          &lt;taskId&gt;_task0&lt;/taskId&gt;
          &lt;rateSpec type=&quot;sto.RateSpec&quot; uuid=&quot;43690689-e50d-4d90-9a6d-9acbae65545d&quot;&gt;
            &lt;period&gt;.01&lt;/period&gt;
            &lt;rateType&gt;ClassicPeriodicDiscrete&lt;/rateType&gt;
          &lt;/rateSpec&gt;
        &lt;/rates&gt;
        &lt;rates type=&quot;sto.ClassicPeriodicDiscreteRate&quot; uuid=&quot;fcf20b98-9ce5-4866-b9f1-19ca3ab08fed&quot;&gt;
          &lt;annotation&gt;D8&lt;/annotation&gt;
          &lt;clockId&gt;GVCU_HIL_simscape::defaultTimer&lt;/clockId&gt;
          &lt;colorIndex&gt;7&lt;/colorIndex&gt;
          &lt;description&gt;Discrete 8&lt;/description&gt;
          &lt;rateIdx&gt;8&lt;/rateIdx&gt;
          &lt;taskId&gt;_task0&lt;/taskId&gt;
          &lt;rateSpec type=&quot;sto.RateSpec&quot; uuid=&quot;f78c04a0-3a1a-4022-8c38-8a4ea00d33ec&quot;&gt;
            &lt;period&gt;.1&lt;/period&gt;
            &lt;rateType&gt;ClassicPeriodicDiscrete&lt;/rateType&gt;
          &lt;/rateSpec&gt;
        &lt;/rates&gt;
        &lt;rates type=&quot;sto.ClassicPeriodicDiscreteRate&quot; uuid=&quot;cc05c093-2d44-497c-97fe-8128007af233&quot;&gt;
          &lt;annotation&gt;D9&lt;/annotation&gt;
          &lt;clockId&gt;GVCU_HIL_simscape::defaultTimer&lt;/clockId&gt;
          &lt;colorIndex&gt;8&lt;/colorIndex&gt;
          &lt;description&gt;Discrete 9&lt;/description&gt;
          &lt;rateIdx&gt;9&lt;/rateIdx&gt;
          &lt;taskId&gt;_task0&lt;/taskId&gt;
          &lt;rateSpec type=&quot;sto.RateSpec&quot; uuid=&quot;4f08f175-c467-43c9-9a90-64b0049e1ffa&quot;&gt;
            &lt;period&gt;1.0&lt;/period&gt;
            &lt;rateType&gt;ClassicPeriodicDiscrete&lt;/rateType&gt;
          &lt;/rateSpec&gt;
        &lt;/rates&gt;
        &lt;schedulingClockId&gt;GVCU_HIL_simscape::defaultTimer&lt;/schedulingClockId&gt;
        &lt;timeKeeperClockId&gt;GVCU_HIL_simscape::defaultTimer&lt;/timeKeeperClockId&gt;
        &lt;elementType&gt;Task&lt;/elementType&gt;
        &lt;identifier&gt;_task0&lt;/identifier&gt;
        &lt;priority&gt;40&lt;/priority&gt;
      &lt;/rootTaskHierarchyElements&gt;
      &lt;taskDependencyGraph type=&quot;sto.SerializedTaskConnectionList&quot; uuid=&quot;5d345145-1b0c-4f6d-905d-7c259bc6924f&quot;&gt;
        &lt;clockIdentifier&gt;ParameterChangeEvent&lt;/clockIdentifier&gt;
        &lt;taskIdentifier&gt;ModelWideParameterChangeEvent&lt;/taskIdentifier&gt;
      &lt;/taskDependencyGraph&gt;
      &lt;taskDependencyGraph type=&quot;sto.SerializedTaskConnectionList&quot; uuid=&quot;65a74cbf-e026-4b79-9f6e-6ec42e1a0a22&quot;&gt;
        &lt;clockIdentifier&gt;GVCU_HIL_simscape::defaultTimer&lt;/clockIdentifier&gt;
        &lt;taskIdentifier&gt;_task0&lt;/taskIdentifier&gt;
      &lt;/taskDependencyGraph&gt;
      &lt;taskPriorityDirection&gt;HighNumberLast&lt;/taskPriorityDirection&gt;
    &lt;/taskRegistry&gt;
  &lt;/sto.Registry&gt;
&lt;/slexec_sto&gt;</timingAndTaskingRegistry>
    <zeroCrossingInfo type="ModelRefInfoRepo.ZeroCrossingInfo" uuid="209c8cb4-eb7a-474a-802c-d76d37ce656f">
      <direction>63</direction>
      <isDiscrete>true</isDiscrete>
      <name>Reset</name>
      <needsSolverReset>true</needsSolverReset>
      <tolerance>-1.0</tolerance>
      <type>1</type>
      <width>1</width>
    </zeroCrossingInfo>
    <FMUBlockMap type="ModelRefInfoRepo.FMUBlockInfo" uuid="1deb9f23-4546-4ce1-8dab-5f34f16d1650"/>
    <codeGenInfo type="ModelRefInfoRepo.CodeGenInformation" uuid="c761041f-d720-4efa-ab5a-0029204bc5d1">
      <needsTaskCounters>true</needsTaskCounters>
    </codeGenInfo>
    <compiledVariantInfos type="ModelRefInfoRepo.CompiledVariantInfoMap" uuid="9d0ecffc-e7cc-4878-beec-c97168efb43f"/>
    <configSettingsForConsistencyChecks type="ModelRefInfoRepo.ConfigSettingsForConsistencyChecks" uuid="dc7cbd8a-9a0a-4c34-96d9-f9d765fb0992">
      <consistentOutportInitialization>true</consistentOutportInitialization>
      <dateTimeAtTZero>0.0</dateTimeAtTZero>
      <dateTimeAtTZero>0.0</dateTimeAtTZero>
      <dateTimeAtTZero>0.0</dateTimeAtTZero>
      <dateTimeAtTZero>0.0</dateTimeAtTZero>
      <dateTimeAtTZero>0.0</dateTimeAtTZero>
      <dateTimeAtTZero>0.0</dateTimeAtTZero>
      <fixedStepSize>.0002</fixedStepSize>
      <frameDiagnosticSetting>2</frameDiagnosticSetting>
      <signalLoggingSaveFormat>2</signalLoggingSaveFormat>
      <simSIMDOptimization>1</simSIMDOptimization>
      <solverName>ode3</solverName>
      <solverType>SOLVER_TYPE_FIXEDSTEP</solverType>
      <hardwareSettings type="ModelRefInfoRepo.HardwareSettings" uuid="9fea55af-5518-4a2a-b345-33ef72932c54">
        <prodBitPerChar>8</prodBitPerChar>
        <prodBitPerDouble>64</prodBitPerDouble>
        <prodBitPerFloat>32</prodBitPerFloat>
        <prodBitPerInt>32</prodBitPerInt>
        <prodBitPerLong>32</prodBitPerLong>
        <prodBitPerLongLong>64</prodBitPerLongLong>
        <prodBitPerPointer>64</prodBitPerPointer>
        <prodBitPerPtrDiffT>64</prodBitPerPtrDiffT>
        <prodBitPerShort>16</prodBitPerShort>
        <prodBitPerSizeT>64</prodBitPerSizeT>
        <prodEndianess>1</prodEndianess>
        <prodShiftRight>true</prodShiftRight>
        <prodWordSize>64</prodWordSize>
      </hardwareSettings>
    </configSettingsForConsistencyChecks>
    <controllableInputRatesMap type="ModelRefInfoRepo.VarTsUIDMap" uuid="bdb4251c-e160-4320-9224-810217b7a56c"/>
    <controllableOutputRatesMap type="ModelRefInfoRepo.VarTsUIDMap" uuid="a5f17cdf-71c9-42e2-beb7-703355863da0"/>
    <dataPortGroup type="ModelRefInfoRepo.DataPortGroup" uuid="56205bd7-15cc-428a-a712-fd1dac7f7461"/>
    <expFcnUnconnectedDataPortGroup type="ModelRefInfoRepo.DataPortGroup" uuid="52a4329e-dcae-4039-ac37-1d856f6d4b8a"/>
    <interfaceParameterInfo type="ModelRefInfoRepo.InterfaceParameterInfo" uuid="0ff45133-bbc9-4e4c-a739-8c932a13a26f">
      <globalVariables type="ModelRefInfoRepo.StructureParameter" uuid="1c9be33e-74f7-467c-9137-2ab523373ff1">
        <datatypeChecksum>3222063392</datatypeChecksum>
        <datatypeChecksum>3478544038</datatypeChecksum>
        <datatypeChecksum>4083112076</datatypeChecksum>
        <datatypeChecksum>291858052</datatypeChecksum>
        <datatypeIsAnonymous>true</datatypeIsAnonymous>
        <datatypeName>struct_7WsordbVTlgRF4Scq3ReHF</datatypeName>
        <dimensions>1</dimensions>
        <dimensions>1</dimensions>
        <isUsed>true</isUsed>
        <numDimensions>2</numDimensions>
        <parameterName>brake</parameterName>
      </globalVariables>
      <globalVariables type="ModelRefInfoRepo.BuiltinParameter" uuid="e43d1953-9ac8-43a7-813f-4a7c477a9134">
        <dimensions>10608</dimensions>
        <dimensions>1</dimensions>
        <isUsed>true</isUsed>
        <numDimensions>2</numDimensions>
        <parameterName>acc_pedal_data</parameterName>
      </globalVariables>
      <globalVariables type="ModelRefInfoRepo.BuiltinParameter" uuid="add12525-a910-486a-8b33-1994a35ce6a0">
        <dimensions>10608</dimensions>
        <dimensions>1</dimensions>
        <isUsed>true</isUsed>
        <numDimensions>2</numDimensions>
        <parameterName>acc_pedal_time</parameterName>
      </globalVariables>
      <globalVariables type="ModelRefInfoRepo.BuiltinParameter" uuid="a16d801e-d3da-4653-972d-c271f58c314a">
        <dimensions>2121</dimensions>
        <dimensions>1</dimensions>
        <isUsed>true</isUsed>
        <numDimensions>2</numDimensions>
        <parameterName>brk_pedal_data</parameterName>
      </globalVariables>
      <globalVariables type="ModelRefInfoRepo.BuiltinParameter" uuid="34426308-3b2c-47f0-a4e3-83b977a73b29">
        <dimensions>2121</dimensions>
        <dimensions>1</dimensions>
        <isUsed>true</isUsed>
        <numDimensions>2</numDimensions>
        <parameterName>brk_pedal_time</parameterName>
      </globalVariables>
      <globalVariables type="ModelRefInfoRepo.BuiltinParameter" uuid="e58cc4cf-71b9-4634-b9cb-82d87fe60e36">
        <dimensions>1</dimensions>
        <dimensions>14</dimensions>
        <isUsed>true</isUsed>
        <numDimensions>2</numDimensions>
        <parameterName>cycle_len</parameterName>
      </globalVariables>
      <globalVariables type="ModelRefInfoRepo.BuiltinParameter" uuid="cb54a044-e998-4f20-bca5-14f8bb301d42">
        <dimensions>1875</dimensions>
        <dimensions>14</dimensions>
        <isUsed>true</isUsed>
        <numDimensions>2</numDimensions>
        <parameterName>cycle_speed_matrix</parameterName>
      </globalVariables>
      <globalVariables type="ModelRefInfoRepo.BuiltinParameter" uuid="0dc099c2-598b-4188-9512-c33e8a65ea3e">
        <dimensions>1875</dimensions>
        <dimensions>14</dimensions>
        <isUsed>true</isUsed>
        <numDimensions>2</numDimensions>
        <parameterName>cycle_time_matrix</parameterName>
      </globalVariables>
      <globalVariables type="ModelRefInfoRepo.BuiltinParameter" uuid="979cc4f7-47d4-4d31-8840-4345876ee08d">
        <dimensions>2121</dimensions>
        <dimensions>1</dimensions>
        <isUsed>true</isUsed>
        <numDimensions>2</numDimensions>
        <parameterName>veh_speed_data</parameterName>
      </globalVariables>
      <globalVariables type="ModelRefInfoRepo.BuiltinParameter" uuid="8c5d1c48-f7ad-4e2e-a7f6-6bae59832b2e">
        <dimensions>2121</dimensions>
        <dimensions>1</dimensions>
        <isUsed>true</isUsed>
        <numDimensions>2</numDimensions>
        <parameterName>veh_speed_time</parameterName>
      </globalVariables>
      <globalVariables type="ModelRefInfoRepo.StructureParameter" uuid="184d6ea8-3ef8-42e5-9acc-71afdfe980fd">
        <datatypeChecksum>2988082086</datatypeChecksum>
        <datatypeChecksum>4143089370</datatypeChecksum>
        <datatypeChecksum>3267514740</datatypeChecksum>
        <datatypeChecksum>131333834</datatypeChecksum>
        <datatypeIsAnonymous>true</datatypeIsAnonymous>
        <datatypeName>struct_N0HXmklnGkVIKPEIZWhbGC</datatypeName>
        <dimensions>1</dimensions>
        <dimensions>1</dimensions>
        <isUsed>true</isUsed>
        <numDimensions>2</numDimensions>
        <parameterName>bat</parameterName>
      </globalVariables>
    </interfaceParameterInfo>
    <messageInfo type="ModelRefInfoRepo.MessageInformation" uuid="eb73fa48-4728-4b75-aff0-7b7a72e4165a"/>
    <methodInfo type="ModelRefInfoRepo.MethodExistenceInfo" uuid="800c2fd3-bb44-4f3c-944b-843251be361f">
      <hasDerivMethod>true</hasDerivMethod>
      <hasDisableMethod>true</hasDisableMethod>
      <hasForcingFunctionMethod>true</hasForcingFunctionMethod>
      <hasProjectionMethod>true</hasProjectionMethod>
      <hasSystemInitializeMethod>true</hasSystemInitializeMethod>
      <hasSystemResetMethod>true</hasSystemResetMethod>
      <hasTerminateMethod>true</hasTerminateMethod>
      <hasUpdateMethod>true</hasUpdateMethod>
    </methodInfo>
    <periodicEventPortUnsupportedBlockInfo type="ModelRefInfoRepo.PeriodicEventPortUnsupportedBlockInfo" uuid="16315878-17d9-4331-9a89-7e38359e5cb8">
      <deterministicRTBs>GVCU_HIL_simscape/Clutch handling/Rate Transition</deterministicRTBs>
      <deterministicRTBs>GVCU_HIL_simscape/Clutch handling/Rate Transition1</deterministicRTBs>
      <deterministicRTBs>GVCU_HIL_simscape/Clutch handling/Rate Transition2</deterministicRTBs>
      <deterministicRTBs>GVCU_HIL_simscape/Clutch handling/Rate Transition3</deterministicRTBs>
      <deterministicRTBs>GVCU_HIL_simscape/Driver/0.01s</deterministicRTBs>
      <deterministicRTBs>GVCU_HIL_simscape/Driver/Rate Transition</deterministicRTBs>
      <deterministicRTBs>GVCU_HIL_simscape/Driver/Rate Transition1</deterministicRTBs>
      <deterministicRTBs>GVCU_HIL_simscape/Inverter/Rate Transition</deterministicRTBs>
      <deterministicRTBs>GVCU_HIL_simscape/Inverter/Rate Transition1</deterministicRTBs>
      <multiRateBlocks>GVCU_HIL_simscape/Driver/Driver/Dec_controller/Relay</multiRateBlocks>
    </periodicEventPortUnsupportedBlockInfo>
    <portGroupsRequireSameRate type="ModelRefInfoRepo.PortGroupsRequireSameRate" uuid="ff2e6ed8-adaa-43d6-bc56-9adf71c50c2c">
      <DSMPortGroups type="ModelRefInfoRepo.NameToPortGroupIdxVectMap" uuid="5e9de166-76ee-4f68-979d-bfe04c0b0c4e"/>
      <GlobalDSMPortGroups type="ModelRefInfoRepo.NameToPortGroupIdxVectMap" uuid="96288534-4796-4d80-aa4f-6ad7ccb8d79c"/>
      <mergedPortGroups type="ModelRefInfoRepo.NameToPortGroupIdxVectMap" uuid="1b04fbbf-50b7-44ea-bea5-6c8ddd593460"/>
    </portGroupsRequireSameRate>
    <rateBasedMdlGlobalDSMRateSpec type="ModelRefInfoRepo.GlobalDSMRateSpecMap" uuid="523f0087-7baf-44e3-8a76-3ba608a0fe3e"/>
    <rateSpecOfGlobalDSMAccessedByDescExpFcnMdlMap type="ModelRefInfoRepo.GlobalDSMRateSpecMap" uuid="cbd7eb97-d6b0-4af0-8f12-a7bcc530ae80"/>
    <rootBlockDiagramInterface type="ci.Model" uuid="7035e1a9-5f7d-4e46-8984-4bb89c12def2">
      <p_RootComponentInterface type="ci.ComponentInterface" uuid="3bf17343-6861-4f46-99a2-ed9f0d1563f3">
        <p_Name>GVCU_HIL_simscape</p_Name>
        <p_Type>ROOT</p_Type>
      </p_RootComponentInterface>
    </rootBlockDiagramInterface>
    <simulinkFunctions type="ModelRefInfoRepo.SimulinkFunctions" uuid="4c962f09-bbf0-4809-aadf-d68b50ddd1b3">
      <compSimulinkFunctionCatalog></compSimulinkFunctionCatalog>
    </simulinkFunctions>
    <sltpContext type="sltp.mm.core.Context" uuid="eaa72d88-4ee5-416d-b060-e92534399baf">
      <priorityDirection>HighNumberLast</priorityDirection>
      <defaultBarrierBehavior type="sltp.mm.core.BarrierBehavior" uuid="7a3e75e8-3266-4ee1-9c0d-56ab676879db"/>
      <defaultEventBehavior type="sltp.mm.core.EventBehavior" uuid="d7ab87b1-5e71-4ca0-9d82-f03c5bd9acc2"/>
      <editorState type="sltp.mm.core.EditorState" uuid="dfddbac0-357d-476b-aee8-f6ce847b5b79">
        <isSynchronized>true</isSynchronized>
        <panelState type="sltp.mm.core.EditorPanelState" uuid="ce5f0e47-f930-4581-a1d3-2284783b58ef"/>
      </editorState>
      <rootTask type="sltp.mm.core.Task" uuid="d68bf30b-f682-4bfc-92a1-8148c2d0e839">
        <context type="sltp.mm.core.Context" uuid="eaa72d88-4ee5-416d-b060-e92534399baf"/>
        <explicit>false</explicit>
        <name>Default</name>
        <priority>-2147483648</priority>
        <subgraph type="sltp.mm.core.Graph" uuid="d49cbe55-bd86-4672-a486-46c034e89138">
          <tasks type="sltp.mm.core.Task" uuid="d09d96af-dd61-4cb6-a76b-31f70fcbd4d1">
            <baseTask>true</baseTask>
            <context type="sltp.mm.core.Context" uuid="eaa72d88-4ee5-416d-b060-e92534399baf"/>
            <explicit>false</explicit>
            <id>1</id>
            <isTimed>true</isTimed>
            <name>Cont</name>
            <priority>40</priority>
            <rates type="sltp.mm.core.Rate" uuid="381169a5-bf02-4e07-b905-615fa2b6ce65">
              <annotation>Cont</annotation>
              <color>255</color>
              <hasBlocks>true</hasBlocks>
              <identifier>Continuous00</identifier>
              <rateIndex>0</rateIndex>
              <rateSpec type="sltp.mm.core.RateSpec">
                <period>0.0</period>
              </rateSpec>
              <sti>0</sti>
            </rates>
            <rates type="sltp.mm.core.Rate" uuid="83fce90c-1ccc-454a-818f-1b21da63e22a">
              <annotation>D1</annotation>
              <color>-12240129</color>
              <hasBlocks>true</hasBlocks>
              <rateIndex>1</rateIndex>
              <rateSpec type="sltp.mm.core.RateSpec">
                <period>.0002</period>
              </rateSpec>
              <sti>1</sti>
            </rates>
            <rates type="sltp.mm.core.Rate" uuid="30998f9d-50ec-4b6f-ad9f-2cc718519e37">
              <annotation>D2</annotation>
              <color>986198527</color>
              <hasBlocks>true</hasBlocks>
              <rateIndex>2</rateIndex>
              <rateSpec type="sltp.mm.core.RateSpec">
                <period>.0004</period>
              </rateSpec>
              <sti>2</sti>
            </rates>
            <rates type="sltp.mm.core.Rate" uuid="46ee3b47-8cec-4a69-b0b1-1950d6566e36">
              <annotation>D3</annotation>
              <color>234946559</color>
              <hasBlocks>true</hasBlocks>
              <rateIndex>3</rateIndex>
              <rateSpec type="sltp.mm.core.RateSpec">
                <period>.001</period>
              </rateSpec>
              <sti>3</sti>
            </rates>
            <rates type="sltp.mm.core.Rate" uuid="eb57aa91-7651-44ee-a4a0-b151e9f0998e">
              <annotation>D4</annotation>
              <color>234946559</color>
              <hasBlocks>true</hasBlocks>
              <rateIndex>4</rateIndex>
              <rateSpec type="sltp.mm.core.RateSpec">
                <period>.002</period>
              </rateSpec>
              <sti>4</sti>
            </rates>
            <rates type="sltp.mm.core.Rate" uuid="809e52f4-fbf4-4f25-a31e-eff10e145032">
              <annotation>D5</annotation>
              <color>234946559</color>
              <hasBlocks>true</hasBlocks>
              <rateIndex>5</rateIndex>
              <rateSpec type="sltp.mm.core.RateSpec">
                <period>.004</period>
              </rateSpec>
              <sti>5</sti>
            </rates>
            <rates type="sltp.mm.core.Rate" uuid="f838220c-171e-41f1-9a85-3a647b9f5693">
              <annotation>D6</annotation>
              <color>234946559</color>
              <hasBlocks>true</hasBlocks>
              <rateIndex>6</rateIndex>
              <rateSpec type="sltp.mm.core.RateSpec">
                <period>.005</period>
              </rateSpec>
              <sti>6</sti>
            </rates>
            <rates type="sltp.mm.core.Rate" uuid="89fe5514-4ed9-4d7d-9d53-b534db2828bb">
              <annotation>D7</annotation>
              <color>234946559</color>
              <hasBlocks>true</hasBlocks>
              <rateIndex>7</rateIndex>
              <rateSpec type="sltp.mm.core.RateSpec">
                <period>.01</period>
              </rateSpec>
              <sti>7</sti>
            </rates>
            <rates type="sltp.mm.core.Rate" uuid="73dada0c-2728-4cf2-86b5-61e6fd17fc86">
              <annotation>D8</annotation>
              <color>234946559</color>
              <hasBlocks>true</hasBlocks>
              <rateIndex>8</rateIndex>
              <rateSpec type="sltp.mm.core.RateSpec">
                <period>.1</period>
              </rateSpec>
              <sti>8</sti>
            </rates>
            <rates type="sltp.mm.core.Rate" uuid="1d74b2c1-05ef-4673-a7e5-28bc0e515af5">
              <annotation>D9</annotation>
              <color>234946559</color>
              <hasBlocks>true</hasBlocks>
              <rateIndex>9</rateIndex>
              <rateSpec type="sltp.mm.core.RateSpec">
                <period>1.0</period>
              </rateSpec>
              <sti>9</sti>
            </rates>
          </tasks>
        </subgraph>
      </rootTask>
    </sltpContext>
    <stateWriterToOwnerMap type="ModelRefInfoRepo.StateWriterInfo" uuid="59d48485-e369-4a3f-aa2d-fec5ca258b75"/>
    <stoClientDataRegistry type="sto.ClientDataRegistry" uuid="d4f36aed-8f58-4202-a83d-79c334daef40">
      <dataSets type="sto.ClientClockNamedDataSet" uuid="070e5d7c-d8f6-46d9-8f45-da5cc580fd12">
        <tag>sltpEvents</tag>
      </dataSets>
      <dataSets type="sto.ClientTaskHierarchyElementNamedDataSet" uuid="eb543c0d-36e4-4a3b-988c-48db02a45574">
        <tag>sltpTaskGroups</tag>
      </dataSets>
      <dataSets type="sto.ClientTaskHierarchyElementNamedDataSet" uuid="2f4a883a-0719-46cd-aef0-f143dd932faa">
        <dSet type="ModelRefInfoRepo.SltpTaskData" uuid="1e4ffa55-3ebe-4fba-a27a-b4a624c8661e"/>
        <tSet type="ModelRefInfoRepo.SltpTaskData" uuid="1e4ffa55-3ebe-4fba-a27a-b4a624c8661e">
          <dataName>Cont</dataName>
          <linkedSet type="sto.ClientTaskHierarchyElementNamedDataSet" uuid="2f4a883a-0719-46cd-aef0-f143dd932faa"/>
          <id type="sto.TaskHierarchyElementId">
            <clockId>GVCU_HIL_simscape::defaultTimer</clockId>
            <id>_task0</id>
          </id>
        </tSet>
        <tag>sltpTasks</tag>
      </dataSets>
    </stoClientDataRegistry>
    <varTsUIDMap type="ModelRefInfoRepo.VarTsUIDMap" uuid="f19caad9-1122-47b5-8217-4f1637e562ba"/>
  </ModelRefInfoRepo.ModelRefInfoRoot>
</MF0>